ElecSolver/FrequencySystemBuilder.py
ElecSolver/NetlistParser.py
ElecSolver/TemporalSystemBuilder.py
ElecSolver/__init__.py
ElecSolver/utils.py
elecsolver-1.0.6.dist-info/licenses/LICENSE.txt
elecsolver-1.0.6.dist-info/METADATA
elecsolver-1.0.6.dist-info/WHEEL
elecsolver-1.0.6.dist-info/top_level.txt
elecsolver-1.0.6.dist-info/RECORD
