Metadata-Version: 2.4
Name: ElecSolver
Version: 1.0.6
Summary: Formalizes electric systems as linear problems for temporal and frequency-domain studies.
Author-email: William Piat <william.piat3@gmail.com>
License: MIT
Project-URL: Homepage, https://github.com/williampiat3/ElecSolver
Platform: Linux
Platform: Unix
Classifier: Programming Language :: Python :: 3
Classifier: Operating System :: POSIX
Classifier: License :: OSI Approved :: MIT License
Classifier: Intended Audience :: Science/Research
Classifier: Topic :: Scientific/Engineering :: Physics
Requires-Python: >=3.9
License-File: LICENSE.txt
Requires-Dist: numpy
Requires-Dist: scipy
Requires-Dist: networkx
Provides-Extra: dev
Requires-Dist: pytest; extra == "dev"
Requires-Dist: python-mumps; extra == "dev"
Dynamic: license-file
